[
    {
        "id": "393",
        "code": "SHA0400-1",
        "name": "上海星品宝黎环球港",
        "phone_seal": "021-54865009",
        "phone_service": "021-54865058",
        "lng": "121.419129",
        "lat": "31.239446",
        "fullname": "广汽埃安上海星品宝黎环球港商超展示中心",
        "address": "由上海市普陀区中山北路3300号上海环球港B1层变更至上海市普陀区中山北路3300号上海环球港4层",
        "dealer_order": null,
        "is_dealer": "2",
        "is_lx_special_store": "0",
        "service_id": "",
        "region": "华东大区",
        "region_id": "1",
        "distance": 2.38,
        "limit_area": "0",
        "chargingNum": 0
    },
    {
        "id": "129",
        "code": "SHA0500",
        "name": "上海君和",
        "phone_seal": "021-57529922",
        "phone_service": "021-57529933",
        "lng": "121.350176",
        "lat": "31.281833",
        "fullname": "广汽埃安上海君和体验中心",
        "address": " 上海市普陀区金昌路1858号",
        "dealer_order": null,
        "is_dealer": "2",
        "is_lx_special_store": "1",
        "service_id": "",
        "region": "华东大区",
        "region_id": "1",
        "distance": 5.72,
        "limit_area": "0",
        "chargingNum": 0
    },
    {
        "id": "259",
        "code": "SHA3000",
        "name": "上海长岚",
        "phone_seal": "021-33581833",
        "phone_service": "021-33581877",
        "lng": "121.351297",
        "lat": "31.181892",
        "fullname": "广汽埃安上海长岚展示中心",
        "address": "上海市闵行区沪青平公路415-433号",
        "dealer_order": null,
        "is_dealer": "2",
        "is_lx_special_store": "0",
        "service_id": "",
        "region": "华东大区",
        "region_id": "1",
        "distance": 8.67,
        "limit_area": "0",
        "chargingNum": 0
    },
    {
        "id": "469",
        "code": "SHA0900-1",
        "name": "上海晋熙万泰",
        "phone_seal": "13321907756",
        "phone_service": "",
        "lng": "121.481949",
        "lat": "31.289677",
        "fullname": "广汽埃安上海晋熙万泰商超展示中心",
        "address": "上海市虹口区广灵二路259号（万泰广场）",
        "dealer_order": null,
        "is_dealer": "2",
        "is_lx_special_store": "0",
        "service_id": "",
        "region": "华东大区",
        "region_id": "1",
        "distance": 9.23,
        "limit_area": "0",
        "chargingNum": 0
    },
    {
        "id": "407",
        "code": "SHA0400-2",
        "name": "上海星品宝黎百联南方",
        "phone_seal": "18621958621",
        "phone_service": "18621958621",
        "lng": "121.406909",
        "lat": "31.137936",
        "fullname": "广汽埃安上海星品宝黎百联南方商超展示中心",
        "address": "上海市闵行区沪闵路7250号百联南方购物中心2区1F-002号",
        "dealer_order": null,
        "is_dealer": "2",
        "is_lx_special_store": "0",
        "service_id": "",
        "region": "华东大区",
        "region_id": "1",
        "distance": 12.42,
        "limit_area": "0",
        "chargingNum": 0
    },
    {
        "id": "127",
        "code": "SHA0200",
        "name": "上海弘仁宝裕",
        "phone_seal": "400-186-7988",
        "phone_service": "400-186-7988",
        "lng": "121.473604",
        "lat": "31.340726",
        "fullname": "广汽埃安上海弘仁宝裕体验中心",
        "address": " 上海市宝山区江杨南路1505号",
        "dealer_order": null,
        "is_dealer": "2",
        "is_lx_special_store": "1",
        "service_id": "",
        "region": "华东大区",
        "region_id": "1",
        "distance": 12.49,
        "limit_area": "0",
        "chargingNum": 0
    },
    {
        "id": "412",
        "code": "SHA0500-1",
        "name": "上海君和五角场万达",
        "phone_seal": "021-57529922",
        "phone_service": "021-57529933",
        "lng": "121.519349",
        "lat": "31.307215",
        "fullname": "广汽埃安上海君和五角场万达商超展示中心",
        "address": "上海市杨浦区淞沪路77号五角场万达广场",
        "dealer_order": null,
        "is_dealer": "2",
        "is_lx_special_store": "0",
        "service_id": "",
        "region": "华东大区",
        "region_id": "1",
        "distance": 13.28,
        "limit_area": "0",
        "chargingNum": 0
    },
    {
        "id": "130",
        "code": "SHA0400",
        "name": "上海星品宝黎",
        "phone_seal": "400-861-7988",
        "phone_service": "400-861-7988",
        "lng": "121.358744",
        "lat": "31.126661",
        "fullname": "广汽埃安上海星品宝黎体验中心",
        "address": "上海市闵行区黎安路1399弄18号",
        "dealer_order": null,
        "is_dealer": "2",
        "is_lx_special_store": "0",
        "service_id": "",
        "region": "华东大区",
        "region_id": "1",
        "distance": 14.12,
        "limit_area": "0",
        "chargingNum": 0
    },
    {
        "id": "434",
        "code": "SHA0110",
        "name": "上海炜业龙阳",
        "phone_seal": "50591888",
        "phone_service": "50594995",
        "lng": "121.541508",
        "lat": "31.204275",
        "fullname": "广汽埃安上海炜业龙阳体验中心",
        "address": "上海市浦东新区龙阳路1277号",
        "dealer_order": null,
        "is_dealer": "2",
        "is_lx_special_store": "0",
        "service_id": "",
        "region": "华东大区",
        "region_id": "1",
        "distance": 14.62,
        "limit_area": "0",
        "chargingNum": 0
    },
    {
        "id": "387",
        "code": "SHA0600-1",
        "name": "上海劲立徐汇华泾天街",
        "phone_seal": "021-59200167",
        "phone_service": "021-59200177",
        "lng": "121.457453",
        "lat": "31.125649",
        "fullname": "广汽埃安上海劲立徐汇华泾天街商场展示中心",
        "address": "上海市徐汇区华泾路459号L102龙湖上海华泾天街",
        "dealer_order": null,
        "is_dealer": "2",
        "is_lx_special_store": "0",
        "service_id": "",
        "region": "华东大区",
        "region_id": "1",
        "distance": 14.9,
        "limit_area": "0",
        "chargingNum": 0
    },
    {
        "id": "128",
        "code": "SHA0600",
        "name": "上海劲立",
        "phone_seal": "021-59200167",
        "phone_service": "021-59200177",
        "lng": "121.220134",
        "lat": "31.253820",
        "fullname": "广汽埃安上海劲立体验中心",
        "address": " 上海市青浦区嘉松中路799弄26号",
        "dealer_order": null,
        "is_dealer": "2",
        "is_lx_special_store": "0",
        "service_id": "",
        "region": "华东大区",
        "region_id": "1",
        "distance": 16.81,
        "limit_area": "0",
        "chargingNum": 0
    },
    {
        "id": "427",
        "code": "SHA0600-2",
        "name": "上海劲立颛桥万达",
        "phone_seal": "021-59200167",
        "phone_service": "021-59200177",
        "lng": "121.412839",
        "lat": "31.077149",
        "fullname": "广汽埃安上海劲立颛桥万达商超展示中心",
        "address": "上海市闵行区颛兴东路1570号（颛桥万达）",
        "dealer_order": null,
        "is_dealer": "2",
        "is_lx_special_store": "0",
        "service_id": "",
        "region": "华东大区",
        "region_id": "1",
        "distance": 19.2,
        "limit_area": "0",
        "chargingNum": 0
    },
    {
        "id": "126",
        "code": "SHA6100",
        "name": "上海成套",
        "phone_seal": "400-897-1060",
        "phone_service": "021-68389558",
        "lng": "121.537869",
        "lat": "31.040183",
        "fullname": "广汽埃安上海成套体验中心",
        "address": " 上海市闵行区三鲁公路889号",
        "dealer_order": null,
        "is_dealer": "2",
        "is_lx_special_store": "0",
        "service_id": "",
        "region": "华东大区",
        "region_id": "1",
        "distance": 26.83,
        "limit_area": "0",
        "chargingNum": 0
    },
    {
        "id": "424",
        "code": "SHA0900",
        "name": "上海晋熙",
        "phone_seal": "021-68041618",
        "phone_service": "021-68041619",
        "lng": "121.595669",
        "lat": "31.075394",
        "fullname": "广汽埃安上海晋熙上海车市体验中心",
        "address": "上海市浦东新区沪南路4789弄311号",
        "dealer_order": null,
        "is_dealer": "2",
        "is_lx_special_store": "0",
        "service_id": "",
        "region": "华东大区",
        "region_id": "1",
        "distance": 27.03,
        "limit_area": "0",
        "chargingNum": 0
    }
]